<?xml version="1.0" encoding="UTF-8"?>
<subject>
  <name>confucius</name>
  <title>孔子</title>
  <!-->source: baidu baike<-->
  <image>confucius.jpeg</image>
  <intro>
    曲阜，东临蒙山，北靠岱岳，南阻峰山，西绕沂泗。那里土地肥沃，物产丰富， 是一个得天独厚的天然粮仓，很早就成了中华民族的发祥地之一。
    早在公元前四千 多年，这里便出现了“大汶口文化”等原始文明。稍后这里又是传说中古帝少吴氏 定都之处，号称“少昊之墟”。历夏经商，曲阜又成为鲁周公封国的首都，肩负起 镇抚东夷，拱卫王室的历史重任。
    在春秋时期，曲阜以其所保存的西周礼乐资料， 逐渐成为中国文化造型的摇篮。利用这些丰富的历史遗产，完成这种造型工程的总 设计师，便是世界文化名人、儒学宗师——孔子。

    孔子，名丘，字仲尼。他一生并不显赫，但司马迁的《史记》，为他作有《孔 子世家》，与诸侯同列，以示对他的特殊优待。
    司马迁说：“天下君王至于贤人众 矣，当时则荣，没则已焉。孔子布衣，传十余世，学者宗之。自天子王侯，中国言 六艺者，折中于夫子，可谓至圣矣！”
    古往今来君王贤人不少，在生时显赫一世， 风光一时，不可一世，但是死后就消声匿迹，形同粪土。孔子则相反，在世坎坷， 死后却十分尊荣。
    历代统治者对他加号进爵，黄屋左蠢，有王者之尊。其后代享其 余泽，至今世世不绝。在中国所有宗法家谱中，可能只有孔氏家谱才是货真价实、 一脉传衍的第一家族。其原因何在呢？
    正如太史公揭示的那样：孔子删定了六经， 为天下万世提供了研之不尽的绝代经典；孔子一生嘉言效范，为天下万世树立了仰 之行之的不朽榜样。
    他是先师，他是圣人，立德立言，足以垂法后世，宜其子子孙 孙传行无穷也。
  </intro>
  <link>
    <text>至圣先师孔子</text>
    <url>http://www.quanxue.cn/CT_RuJia/LiDai/LiDai02.html</url>
  </link>
  <links>
    <value>
      <text>至圣先师孔子</text>
      <url>http://www.quanxue.cn/CT_RuJia/LiDai/LiDai02.html</url>
    </value>
  </links>
</subject>